scorecardpyEC/Bin.py
scorecardpyEC/__init__.py
scorecardpyEC-1.1.1.dist-info/LICENSE
scorecardpyEC-1.1.1.dist-info/METADATA
scorecardpyEC-1.1.1.dist-info/WHEEL
scorecardpyEC-1.1.1.dist-info/top_level.txt
scorecardpyEC-1.1.1.dist-info/RECORD
