Metadata-Version: 2.1
Name: scorecardpyEC
Version: 1.1.1
Summary: 为评分卡项目https://github.com/ShichenXie/scorecardpy提供常用的额外的工具组件。可以帮助评分卡开发人员提高开发效率
Home-page: https://github.com/wangwenhao-DATA-OG/scorecardpyEC
Author: 王文皓(wangwenhao)
Author-email: DATA-OG@139.com
License: UNKNOWN
Keywords: score card,scorecardpy
Platform: UNKNOWN
Classifier: Programming Language :: Python :: 3
Classifier: License :: OSI Approved :: Apache Software License
Classifier: Operating System :: OS Independent
Requires-Python: >=3.4
Requires-Dist: scorecardpy (>=0.1.8)
Requires-Dist: pandas (>=0.25.1)
Requires-Dist: numpy (>=1.17.4)
